{
  "slug": "anti-skate",
  "term": "Anti",
  "summary": "A spring- or magnet-based control on turntables that counteracts the inward",
  "definition": "A spring- or magnet-based control on turntables that counteracts the inward pull on the tonearm caused by groove friction, helping the stylus stay centered in the groove.",
  "tags": [
    "equipment",
    "dj-related",
    "pressing"
  ],
  "created": "2026-01-05",
  "updated": "2026-01-05",
  "see_also": [
    "tracking-force",
    "tonearm",
    "groove-wear"
  ],
  "regions": [
    "US"
  ]
}
