{
  "slug": "compilation-album",
  "term": "Compilation Album",
  "summary": "An LP or multi-disc set collecting songs from various artists or sessions.",
  "definition": "An LP or multi-disc set collecting songs from various artists or sessions — often themed by hits, genre, or label samplers.",
  "tags": [
    "collecting",
    "cultural"
  ],
  "created": "2026-01-05",
  "updated": "2026-01-05",
  "see_also": [
    "anthology",
    "sampler",
    "box-set"
  ],
  "regions": [
    "US"
  ],
  "pos": "noun"
}
