{
  "slug": "heavyweight-vinyl-180-gram-200-gram",
  "term": "Heavyweight Vinyl",
  "summary": "'**noun / marketing term.** Records pressed on thicker, heavier PVC biscuit.",
  "definition": "**noun / marketing term.** Records pressed on thicker, heavier PVC biscuit — typically 180 g or 200 g — marketed for improved stability, flatter profiles, and premium feel.",
  "tags": [
    "pressing"
  ],
  "created": "2026-01-05",
  "updated": "2026-01-05",
  "see_also": [
    "audiophile-pressing",
    "virgin-vinyl",
    "flatness"
  ],
  "regions": [
    "US"
  ],
  "pos": "noun"
}
