{
  "slug": "kiss-style-picture-disc",
  "term": "KISS-Style Picture Disc",
  "summary": "'**noun / cultural.** A reference to the band KISS’s hugely popular late-’70s.",
  "definition": "**noun / cultural.** A reference to the band KISS’s hugely popular late-’70s U.S. picture-disc LPs that sparked a mass trend of collectible rock picture discs.",
  "tags": [
    "collecting"
  ],
  "created": "2026-01-05",
  "updated": "2026-01-05",
  "see_also": [
    "picture-disc",
    "color-vinyl-pressing",
    "collector-variant"
  ],
  "regions": [
    "US"
  ],
  "pos": "noun"
}
